html_to_md_converter/__init__.py
html_to_md_converter/html_to_md_converter.py
html_to_md_converter-0.1.3.dist-info/LICENSE
html_to_md_converter-0.1.3.dist-info/METADATA
html_to_md_converter-0.1.3.dist-info/WHEEL
html_to_md_converter-0.1.3.dist-info/top_level.txt
html_to_md_converter-0.1.3.dist-info/RECORD
