Metadata-Version: 2.1
Name: html-to-md-converter
Version: 0.1.3
Summary: A small tool that converts *.html-files to *.md-files
Home-page: https://github.com/sebastiankulla/html_to_md_converter
Author: Sebastian Kulla
Author-email: sebastiankulla90@gmail.com
License: MIT license
Keywords: html_to_md_converter
Platform: UNKNOWN
Classifier: Development Status :: 2 - Pre-Alpha
Classifier: Intended Audience :: Developers
Classifier: License :: OSI Approved :: MIT License
Classifier: Natural Language :: English
Classifier: Programming Language :: Python :: 3
Classifier: Programming Language :: Python :: 3.6
Classifier: Programming Language :: Python :: 3.7
Classifier: Programming Language :: Python :: 3.8
Requires-Python: >=3.6
License-File: LICENSE
